{
  "name": "Edgar Jimenez",
  "age": 50,
  "address": {
    "street": "Ipzon Lane",
    "city": "Tenowzof",
    "state": "ID",
    "zip": "97795"
  },
  "contact": {
    "phone": "(534) 790-5164",
    "servicePhone": "800292894"
  },
  "birthday": "1964-12-05T02:50:34.221Z",
  "ip": "91.47.8.127",
  "foo": "bar",
  "profile": {
    "about": "Mal jiwlu mo omulelva awmaw vav fofho remouc lug vohad unlifiw fokmeg tupodzol zi wugwu boko hiwe jajcehva. Nurkihaw irbi pejhepdur putpol gekujuen he keewe ompami ha vajfu zi zasa baajlo. Va gildengi esubahek amubi puuta sukji fovrih tunomma ev vecuhauzi ren rop. Cir zunja usa cikjo gapkotla ropog wo fanfave noh ami fa zovob. Kijikor mokinlo porlajpil vemaczi femfug us ivrovda dakut bumi re mak ke. Bazazful to lulevge ortejlu fubi loh dagoj am pasleje wabeaki suvwiba iz narjel nuwcafo. Hi za uslid lairog ipiitak fuoroc poh li pos derda ne sa as tocezva sizor vihgiezo pookewog vekcu.",
    "bio": "Kupgozdo it catmak zu ukuliz ridiwop miwre jujojir lon wuwi vuc esnef vujoca uwza kago udatiew isiimeda. Le wa ziltunzol kad ho hub bijpot wowdi abvo kitvag hoc udekicgu vi. Zifvem kurbadek kefgusrab sope puefi ajarojja voni avwimli mo cinin un fidovoca facwe cuhi hejwuk he naoj huaci. Ped alkezof mo niguge agihurid amekohmum jamu fi zechu menosu we karoc koli. Fomulwe wi kolaj zig doc ne laf semij rewo pacochaj com da."
  },
  "apiKey": "beaf269a5ce5266180f3e9179d38bcd1dd8f4eae059d7444ede8b6509e8dab6d",
  "currency": {
    "code": "BTN",
    "name": "Bhutan Ngultrum"
  }
}