{
  "name": "Bertha Kelly",
  "age": 48,
  "address": {
    "street": "Upevi Junction",
    "city": "Hodvegkut",
    "state": "KY",
    "zip": "66542"
  },
  "contact": {
    "phone": "(753) 409-1803",
    "servicePhone": "800814426"
  },
  "birthday": "2003-06-24T03:19:45.577Z",
  "ip": "182.81.186.146",
  "foo": "bar",
  "profile": {
    "about": "Vu ju verban noagi ganilte teno ji cupe danerufa bop tailu kardevvu ahce ine ivu ru. Bac fus upgefvin kudi nob gakogaiv curaz vegpa dal ibzu pi opojeb looz ko jacuv. Ler penune temje hen calmohoge awolo cod zaar ik iwulepwo duk dauzgo samud buufvol wedis. Lu egzi fuwmu elida vumifzan lozri les nefedu kokum fohejoc kiepute hug wonmof. Of bona vacvumes luwekcu talejo komepop pafuho facag tot id werapu le bajnu. Mebleca vuzna kor fehimo wepas imi kalogil koc vod gudukte fahreja rewe avi.",
    "bio": "Hupulu cozeb sikam ci bel bahboari age ojasza heka ti pi omuvutizi. Uzbokkam roupo ridfab fekki hil ziz ta uce zilicko fak re ezfes awiba zeojo tebvig offediw. Wirfo ge no vorim leidazak omutar fih pajiz ho cis voeko ejooruhev delic jetloiga ojovo tewzi."
  },
  "apiKey": "c453a4e6b318a29135c7b43121cb30a3acb2f65b8fe6480a8036fe267574d124",
  "currency": {
    "code": "TVD",
    "name": "Tuvalu Dollar"
  }
}