{
  "name": "Lewis Park",
  "age": 65,
  "address": {
    "street": "Ehuveh Glen",
    "city": "Zabagein",
    "state": "DE",
    "zip": "77466"
  },
  "contact": {
    "phone": "(737) 801-6381",
    "servicePhone": "800422343"
  },
  "birthday": "1964-06-26T20:56:59.124Z",
  "ip": "19.46.166.172",
  "foo": "bar",
  "profile": {
    "about": "Pi enu tewzitin opefe dup iceig fuh go da lokoc as etfuv go kiszusog be rocwe wepwe. Husdoce eho jibupu iwfi vi vumko magaruj ko jivotgej god mu fufos sen muomuwu. Gugafdu po nebiggum bog jisbahud peugitow made fankag wu hinikgin uctoka mojwo weruwpuk difsoppeh. Hesaru hape ati hegrufi eh gelnutwu ifezobpot ba ge lod apiptot nitug gowod fos. Pir edopap ubusti os tuj kaluv un pikluszaf gohufotur urihenfat ulorwow ejota opa vuz fajcuru ti jamgaoba. Tolvotem lor tiube ju wucucem serve ebasav vaj opsov gakti zijvecmu fevke sibkik jin hufuvrow tulfincu. Duz ot gobpe hor sev donag absepfig relaza fad de itaki roewce aka.",
    "bio": "Durzaip wimno ibze ci riridcoj ritedi zow har tovegcu pi zaelohat zibow wi pan cug. Larluz po lurlen loledob ehri ji gapka nuhfu duho susied ebu en wa. Ruta kene zu sootawu nec val lig fa milbabiw suzu lap iv. Delja vamdek li jiv sur gili ab cucacaf cec le vef dagsebo wafvoz jizmujgih."
  },
  "apiKey": "7a02d9d7db78bb86edf0c41c881c64313730ea051ea0b3bed1ba551e085be280",
  "currency": {
    "code": "BIF",
    "name": "Burundi Franc"
  }
}