{
  "name": "Carrie Maldonado",
  "age": 18,
  "address": {
    "street": "Ojsi Glen",
    "city": "Puhurkib",
    "state": "IN",
    "zip": "52937"
  },
  "contact": {
    "phone": "(906) 875-3196",
    "servicePhone": "800191924"
  },
  "birthday": "1988-05-09T13:16:37.216Z",
  "ip": "7.182.44.44",
  "foo": "bar",
  "profile": {
    "about": "Gapohed acoleb pur goreda cus jonuc fuv ubowi leppib na idsemzi ol. Kaeji hebkala beg mi ih cozak capuhpa ru fifpisize le vif ne sezoame jemsejezi ruskewe mevwac. Kinbo iwa guked ve jutusatu ogijokpuv jeruvni dih fapmo fagesvu wu kizbih lav ju zudogud bu dehpi je.",
    "bio": "Anduble ewhij butetucig te uz hu igvet uze ot de musaal zupvu po. Faf se teni comaho keb ho wotiwa ezcen uvaewamof ip fuljoc tomiji larcutu vol. Im ehdorke wa ondazeh do ej iwpajom odcuot se bopne haw gemehpa nozifokup ranme wan diriz. Suzkogsoh arupo loejo owimwe dup oj comku sevhugo re nola holwikpo tepiwic jator jilug uva ruv zusopo epno."
  },
  "apiKey": "bdd4c02deb13e86d831de97e6aa86d442c9578fb144a68d4b8e3cd5fede14c01",
  "currency": {
    "code": "JMD",
    "name": "Jamaica Dollar"
  }
}